mytelegraph-0.0.8.data/scripts/posting
telegraph/__init__.py
telegraph/api.py
telegraph/conf.py
telegraph/exceptions.py
telegraph/helper.py
telegraph/main.py
telegraph/upload.py
telegraph/utils.py
mytelegraph-0.0.8.dist-info/METADATA
mytelegraph-0.0.8.dist-info/WHEEL
mytelegraph-0.0.8.dist-info/top_level.txt
mytelegraph-0.0.8.dist-info/RECORD
